pygridfit/__init__.py
pygridfit/gridfit.py
pygridfit/interpolation.py
pygridfit/regularizers.py
pygridfit/solvers.py
pygridfit/utils.py
pygridfit-0.1.6.dist-info/METADATA
pygridfit-0.1.6.dist-info/WHEEL
pygridfit-0.1.6.dist-info/licenses/LICENSE
pygridfit-0.1.6.dist-info/RECORD
