Metadata-Version: 2.4
Name: pygridfit
Version: 0.1.6
Summary: Python Port of gridfit (John D'Errico, 2006)
License-File: LICENSE
Requires-Python: >=3.10.0
Requires-Dist: matplotlib>=3.9.4
Requires-Dist: numpy>=2.0.2
Requires-Dist: pytest>=8.3.5
Requires-Dist: scipy>=1.13.2
Requires-Dist: watermark>=2.5.0
Provides-Extra: dev
Requires-Dist: maturin; extra == 'dev'
Requires-Dist: pytest; extra == 'dev'
Requires-Dist: ruff; extra == 'dev'
Requires-Dist: twine; extra == 'dev'
Provides-Extra: scikit-sparse
Requires-Dist: scikit-sparse>=0.4.15; extra == 'scikit-sparse'
